calendariofinanceiro/__init__.py
calendariofinanceiro/calendariofinanceiro.py
calendariofinanceiro/feriados_off.py
calendariofinanceiro/feriados_off.pyi
calendariofinanceiro/feriados_on.py
calendariofinanceiro/feriados_on.pyi
calendariofinanceiro-0.3.1.dist-info/LICENSE
calendariofinanceiro-0.3.1.dist-info/METADATA
calendariofinanceiro-0.3.1.dist-info/WHEEL
calendariofinanceiro-0.3.1.dist-info/RECORD
