Metadata-Version: 2.1
Name: calendariofinanceiro
Version: 0.3.1
Summary: O pacote CalendarioFinanceiro é uma ferramenta Python projetada para facilitar a manipulação de datas financeiras em diferentes calendários, como 'onshore' (Brasil) e 'offshore'. Com este pacote, você pode realizar operações como adicionar dias úteis a uma data, criar listas de dias úteis entre intervalos de datas e muito mais. Ele é uma solução eficiente para lidar com cálculos de datas em cenários financeiros, onde a consideração de dias úteis e feriados é essencial.
Author: eduardo.barreto
Author-email: edugobarreto@gmail.com
Requires-Python: >=3.8,<4.0
Classifier: Programming Language :: Python :: 3
Classifier: Programming Language :: Python :: 3.8
Classifier: Programming Language :: Python :: 3.9
Classifier: Programming Language :: Python :: 3.10
Classifier: Programming Language :: Python :: 3.11
Classifier: Programming Language :: Python :: 3.12
Requires-Dist: workdays (>=1.4,<2.0)
